{
"type": "FeatureCollection",
"crs": { "type": "name", "properties": { "name": "urn:ogc:def:crs:OGC:1.3:CRS84" } },
"features": [
{ "type": "Feature", "properties": { "name": "Partington Children's Centre", "address": "Central Road, Partington, Manchester", "postcode": "M31 4FL", "telephone": "0161-912-2122", "unique_reference_number": 22329 }, "geometry": { "type": "Point", "coordinates": [ -2.425432575765194, 53.41768051190904 ] } },
{ "type": "Feature", "properties": { "name": "Stretford Children's Centre", "address": "9 Poplar Road, Stretford", "postcode": "M32 9AN", "telephone": "0161-912-5020", "unique_reference_number": 22963 }, "geometry": { "type": "Point", "coordinates": [ -2.313931361729267, 53.440847811658038 ] } }
]
}
